ShynaBackEnd/ShynaCheckOnline.py
ShynaBackEnd/ShynaDB.py
ShynaBackEnd/ShynaSpeak.py
ShynaBackEnd/ShynaTime.py
ShynaBackEnd/Shyna_CPUInfo.py
ShynaBackEnd/Shyna_DiskInfo.py
ShynaBackEnd/Shyna_Memory_Info.py
ShynaBackEnd/__init__.py
ShynaBack-0.2.dist-info/LICENSE
ShynaBack-0.2.dist-info/METADATA
ShynaBack-0.2.dist-info/WHEEL
ShynaBack-0.2.dist-info/top_level.txt
ShynaBack-0.2.dist-info/RECORD
