Metadata-Version: 2.1
Name: ShynaBack
Version: 0.2
Summary: Shyna Backend functionality Package
Home-page: UNKNOWN
Author: Shivam Sharma
Author-email: shivamsharma1913@gmail.com
License: UNKNOWN
Platform: UNKNOWN
Requires-Dist: google-speech
Requires-Dist: jinja2
Requires-Dist: mysql-connector-python
Requires-Dist: nltk
Requires-Dist: PyAudio
Requires-Dist: sox
